[{"action":true,"timeAppLastUsed":"immediate","timeOfDay":"night","dayOfWeek":4,"clickCount_prev2":384,"totalSignificantAppLaunchCount_prev2":30,"phoneUsageTime_prev2":160327,"unlockCount_prev2":5,"uniqueAppsLaunched_prev2":9},{"action":false,"timeAppLastUsed":"within 24 hours","timeOfDay":"early-morning","dayOfWeek":5,"clickCount_prev2":130,"totalSignificantAppLaunchCount_prev2":2,"phoneUsageTime_prev2":110588,"unlockCount_prev2":1,"uniqueAppsLaunched_prev2":3},{"action":true,"timeAppLastUsed":"immediate","timeOfDay":"morning","dayOfWeek":5,"clickCount_prev2":2610,"totalSignificantAppLaunchCount_prev2":54,"phoneUsageTime_prev2":882681,"unlockCount_prev2":15,"uniqueAppsLaunched_prev2":17},{"action":true,"timeAppLastUsed":"within half hour","timeOfDay":"afternoon","dayOfWeek":5,"clickCount_prev2":2175,"totalSignificantAppLaunchCount_prev2":50,"phoneUsageTime_prev2":341280,"unlockCount_prev2":14,"uniqueAppsLaunched_prev2":15},{"action":true,"timeAppLastUsed":"immediate","timeOfDay":"evening","dayOfWeek":5,"clickCount_prev2":9351,"totalSignificantAppLaunchCount_prev2":86,"phoneUsageTime_prev2":1445336,"unlockCount_prev2":15,"uniqueAppsLaunched_prev2":19},{"action":true,"timeAppLastUsed":"within half hour","timeOfDay":"afternoon","dayOfWeek":6,"clickCount_prev2":3403,"totalSignificantAppLaunchCount_prev2":50,"phoneUsageTime_prev2":641875,"unlockCount_prev2":16,"uniqueAppsLaunched_prev2":14},{"action":true,"timeAppLastUsed":"immediate","timeOfDay":"early-morning","dayOfWeek":0,"clickCount_prev2":2224,"totalSignificantAppLaunchCount_prev2":76,"phoneUsageTime_prev2":743331,"unlockCount_prev2":18,"uniqueAppsLaunched_prev2":17},{"action":false,"timeAppLastUsed":"within 24 hours","timeOfDay":"early-morning","dayOfWeek":0,"clickCount_prev2":70,"totalSignificantAppLaunchCount_prev2":10,"phoneUsageTime_prev2":17524,"unlockCount_prev2":4,"uniqueAppsLaunched_prev2":4},{"action":true,"timeAppLastUsed":"immediate","timeOfDay":"morning","dayOfWeek":0,"clickCount_prev2":7600,"totalSignificantAppLaunchCount_prev2":146,"phoneUsageTime_prev2":1529746,"unlockCount_prev2":35,"uniqueAppsLaunched_prev2":26},{"action":true,"timeAppLastUsed":"immediate","timeOfDay":"afternoon","dayOfWeek":0,"clickCount_prev2":6627,"totalSignificantAppLaunchCount_prev2":90,"phoneUsageTime_prev2":982038,"unlockCount_prev2":16,"uniqueAppsLaunched_prev2":18},{"action":true,"timeAppLastUsed":"immediate","timeOfDay":"evening","dayOfWeek":0,"clickCount_prev2":5698,"totalSignificantAppLaunchCount_prev2":90,"phoneUsageTime_prev2":940864,"unlockCount_prev2":24,"uniqueAppsLaunched_prev2":14},{"action":true,"timeAppLastUsed":"within 24 hours","timeOfDay":"evening","dayOfWeek":0,"clickCount_prev2":3420,"totalSignificantAppLaunchCount_prev2":82,"phoneUsageTime_prev2":662898,"unlockCount_prev2":19,"uniqueAppsLaunched_prev2":15},{"action":true,"timeAppLastUsed":"within half hour","timeOfDay":"evening","dayOfWeek":0,"clickCount_prev2":3420,"totalSignificantAppLaunchCount_prev2":82,"phoneUsageTime_prev2":662898,"unlockCount_prev2":19,"uniqueAppsLaunched_prev2":15},{"action":false,"timeAppLastUsed":"few mins","timeOfDay":"evening","dayOfWeek":0,"clickCount_prev2":3420,"totalSignificantAppLaunchCount_prev2":82,"phoneUsageTime_prev2":662898,"unlockCount_prev2":19,"uniqueAppsLaunched_prev2":15},{"action":true,"timeAppLastUsed":"immediate","timeOfDay":"evening","dayOfWeek":0,"clickCount_prev2":1350,"totalSignificantAppLaunchCount_prev2":34,"phoneUsageTime_prev2":293662,"unlockCount_prev2":12,"uniqueAppsLaunched_prev2":9},{"action":true,"timeAppLastUsed":"immediate","timeOfDay":"morning","dayOfWeek":1,"clickCount_prev2":1560,"totalSignificantAppLaunchCount_prev2":18,"phoneUsageTime_prev2":172291,"unlockCount_prev2":11,"uniqueAppsLaunched_prev2":12},{"action":true,"timeAppLastUsed":"immediate","timeOfDay":"morning","dayOfWeek":1,"clickCount_prev2":1560,"totalSignificantAppLaunchCount_prev2":18,"phoneUsageTime_prev2":172291,"unlockCount_prev2":11,"uniqueAppsLaunched_prev2":12},{"action":true,"timeAppLastUsed":"immediate","timeOfDay":"morning","dayOfWeek":1,"clickCount_prev2":1560,"totalSignificantAppLaunchCount_prev2":18,"phoneUsageTime_prev2":172291,"unlockCount_prev2":11,"uniqueAppsLaunched_prev2":12},{"action":true,"timeAppLastUsed":"immediate","timeOfDay":"morning","dayOfWeek":1,"clickCount_prev2":1560,"totalSignificantAppLaunchCount_prev2":18,"phoneUsageTime_prev2":172291,"unlockCount_prev2":11,"uniqueAppsLaunched_prev2":12},{"action":true,"timeAppLastUsed":"within half hour","timeOfDay":"morning","dayOfWeek":1,"clickCount_prev2":889,"totalSignificantAppLaunchCount_prev2":22,"phoneUsageTime_prev2":83248,"unlockCount_prev2":11,"uniqueAppsLaunched_prev2":8},{"action":true,"timeAppLastUsed":"within few hours","timeOfDay":"afternoon","dayOfWeek":1,"clickCount_prev2":2125,"totalSignificantAppLaunchCount_prev2":29,"phoneUsageTime_prev2":146305,"unlockCount_prev2":11,"uniqueAppsLaunched_prev2":12},{"action":false,"timeAppLastUsed":"within 24 hours","timeOfDay":"afternoon","dayOfWeek":1,"clickCount_prev2":1021,"totalSignificantAppLaunchCount_prev2":28,"phoneUsageTime_prev2":150035,"unlockCount_prev2":9,"uniqueAppsLaunched_prev2":11},{"action":true,"timeAppLastUsed":"immediate","timeOfDay":"evening","dayOfWeek":1,"clickCount_prev2":16704,"totalSignificantAppLaunchCount_prev2":155,"phoneUsageTime_prev2":1774575,"unlockCount_prev2":20,"uniqueAppsLaunched_prev2":25},{"action":true,"timeAppLastUsed":"immediate","timeOfDay":"evening","dayOfWeek":1,"clickCount_prev2":16704,"totalSignificantAppLaunchCount_prev2":155,"phoneUsageTime_prev2":1774575,"unlockCount_prev2":20,"uniqueAppsLaunched_prev2":25},{"action":true,"timeAppLastUsed":"within few hours","timeOfDay":"evening","dayOfWeek":1,"clickCount_prev2":3040,"totalSignificantAppLaunchCount_prev2":50,"phoneUsageTime_prev2":395517,"unlockCount_prev2":15,"uniqueAppsLaunched_prev2":12},{"action":true,"timeAppLastUsed":"within few hours","timeOfDay":"evening","dayOfWeek":1,"clickCount_prev2":480,"totalSignificantAppLaunchCount_prev2":2,"phoneUsageTime_prev2":59353,"unlockCount_prev2":4,"uniqueAppsLaunched_prev2":3},{"action":true,"timeAppLastUsed":"immediate","timeOfDay":"evening","dayOfWeek":1,"clickCount_prev2":480,"totalSignificantAppLaunchCount_prev2":2,"phoneUsageTime_prev2":59353,"unlockCount_prev2":4,"uniqueAppsLaunched_prev2":3},{"action":false,"timeAppLastUsed":"within 24 hours","timeOfDay":"evening","dayOfWeek":2,"clickCount_prev2":630,"totalSignificantAppLaunchCount_prev2":25,"phoneUsageTime_prev2":63200,"unlockCount_prev2":11,"uniqueAppsLaunched_prev2":11},{"action":true,"timeAppLastUsed":"immediate","timeOfDay":"evening","dayOfWeek":4,"clickCount_prev2":496,"totalSignificantAppLaunchCount_prev2":69,"phoneUsageTime_prev2":659090,"unlockCount_prev2":32,"uniqueAppsLaunched_prev2":17},{"action":false,"timeAppLastUsed":"within last week","timeOfDay":"evening","dayOfWeek":5,"clickCount_prev2":3860,"totalSignificantAppLaunchCount_prev2":135,"phoneUsageTime_prev2":1781676,"unlockCount_prev2":23,"uniqueAppsLaunched_prev2":20},{"action":true,"timeAppLastUsed":"within few hours","timeOfDay":"night","dayOfWeek":5,"clickCount_prev2":460,"totalSignificantAppLaunchCount_prev2":15,"phoneUsageTime_prev2":161427,"unlockCount_prev2":7,"uniqueAppsLaunched_prev2":6},{"action":true,"timeAppLastUsed":"immediate","timeOfDay":"morning","dayOfWeek":6,"clickCount_prev2":2716,"totalSignificantAppLaunchCount_prev2":81,"phoneUsageTime_prev2":1261053,"unlockCount_prev2":15,"uniqueAppsLaunched_prev2":17},{"action":true,"timeAppLastUsed":"within half hour","timeOfDay":"afternoon","dayOfWeek":6,"clickCount_prev2":2716,"totalSignificantAppLaunchCount_prev2":81,"phoneUsageTime_prev2":1261053,"unlockCount_prev2":15,"uniqueAppsLaunched_prev2":17},{"action":true,"timeAppLastUsed":"immediate","timeOfDay":"evening","dayOfWeek":6,"clickCount_prev2":4605,"totalSignificantAppLaunchCount_prev2":181,"phoneUsageTime_prev2":1336683,"unlockCount_prev2":42,"uniqueAppsLaunched_prev2":18},{"action":true,"timeAppLastUsed":"immediate","timeOfDay":"evening","dayOfWeek":6,"clickCount_prev2":4605,"totalSignificantAppLaunchCount_prev2":181,"phoneUsageTime_prev2":1336683,"unlockCount_prev2":42,"uniqueAppsLaunched_prev2":18},{"action":false,"timeAppLastUsed":"immediate","timeOfDay":"evening","dayOfWeek":6,"clickCount_prev2":4605,"totalSignificantAppLaunchCount_prev2":181,"phoneUsageTime_prev2":1336683,"unlockCount_prev2":42,"uniqueAppsLaunched_prev2":18},{"action":false,"timeAppLastUsed":"immediate","timeOfDay":"evening","dayOfWeek":6,"clickCount_prev2":3500,"totalSignificantAppLaunchCount_prev2":171,"phoneUsageTime_prev2":981539,"unlockCount_prev2":43,"uniqueAppsLaunched_prev2":16},{"action":false,"timeAppLastUsed":"immediate","timeOfDay":"evening","dayOfWeek":6,"clickCount_prev2":2400,"totalSignificantAppLaunchCount_prev2":100,"phoneUsageTime_prev2":772169,"unlockCount_prev2":30,"uniqueAppsLaunched_prev2":16},{"action":false,"timeAppLastUsed":"few mins","timeOfDay":"morning","dayOfWeek":0,"clickCount_prev2":1314,"totalSignificantAppLaunchCount_prev2":46,"phoneUsageTime_prev2":363892,"unlockCount_prev2":25,"uniqueAppsLaunched_prev2":17},{"action":false,"timeAppLastUsed":"few mins","timeOfDay":"morning","dayOfWeek":0,"clickCount_prev2":1314,"totalSignificantAppLaunchCount_prev2":46,"phoneUsageTime_prev2":363892,"unlockCount_prev2":25,"uniqueAppsLaunched_prev2":17},{"action":true,"timeAppLastUsed":"immediate","timeOfDay":"morning","dayOfWeek":0,"clickCount_prev2":336,"totalSignificantAppLaunchCount_prev2":23,"phoneUsageTime_prev2":173388,"unlockCount_prev2":13,"uniqueAppsLaunched_prev2":11},{"action":true,"timeAppLastUsed":"immediate","timeOfDay":"evening","dayOfWeek":0,"clickCount_prev2":3156,"totalSignificantAppLaunchCount_prev2":59,"phoneUsageTime_prev2":1065764,"unlockCount_prev2":16,"uniqueAppsLaunched_prev2":18},{"action":true,"timeAppLastUsed":"immediate","timeOfDay":"evening","dayOfWeek":0,"clickCount_prev2":3156,"totalSignificantAppLaunchCount_prev2":59,"phoneUsageTime_prev2":1065764,"unlockCount_prev2":16,"uniqueAppsLaunched_prev2":18},{"action":true,"timeAppLastUsed":"immediate","timeOfDay":"morning","dayOfWeek":1,"clickCount_prev2":1380,"totalSignificantAppLaunchCount_prev2":25,"phoneUsageTime_prev2":295032,"unlockCount_prev2":18,"uniqueAppsLaunched_prev2":10},{"action":true,"timeAppLastUsed":"within half hour","timeOfDay":"morning","dayOfWeek":1,"clickCount_prev2":1487,"totalSignificantAppLaunchCount_prev2":33,"phoneUsageTime_prev2":382897,"unlockCount_prev2":18,"uniqueAppsLaunched_prev2":13},{"action":true,"timeAppLastUsed":"within hour","timeOfDay":"afternoon","dayOfWeek":1,"clickCount_prev2":822,"totalSignificantAppLaunchCount_prev2":48,"phoneUsageTime_prev2":158084,"unlockCount_prev2":11,"uniqueAppsLaunched_prev2":16},{"action":true,"timeAppLastUsed":"within hour","timeOfDay":"afternoon","dayOfWeek":1,"clickCount_prev2":822,"totalSignificantAppLaunchCount_prev2":48,"phoneUsageTime_prev2":158084,"unlockCount_prev2":11,"uniqueAppsLaunched_prev2":16},{"action":true,"timeAppLastUsed":"within few hours","timeOfDay":"evening","dayOfWeek":1,"clickCount_prev2":4624,"totalSignificantAppLaunchCount_prev2":46,"phoneUsageTime_prev2":767043,"unlockCount_prev2":23,"uniqueAppsLaunched_prev2":19},{"action":true,"timeAppLastUsed":"immediate","timeOfDay":"evening","dayOfWeek":1,"clickCount_prev2":4624,"totalSignificantAppLaunchCount_prev2":46,"phoneUsageTime_prev2":767043,"unlockCount_prev2":23,"uniqueAppsLaunched_prev2":19},{"action":false,"timeAppLastUsed":"immediate","timeOfDay":"morning","dayOfWeek":2,"clickCount_prev2":2992,"totalSignificantAppLaunchCount_prev2":29,"phoneUsageTime_prev2":685387,"unlockCount_prev2":18,"uniqueAppsLaunched_prev2":11},{"action":false,"timeAppLastUsed":"immediate","timeOfDay":"morning","dayOfWeek":2,"clickCount_prev2":2992,"totalSignificantAppLaunchCount_prev2":29,"phoneUsageTime_prev2":685387,"unlockCount_prev2":18,"uniqueAppsLaunched_prev2":11},{"action":false,"timeAppLastUsed":"immediate","timeOfDay":"afternoon","dayOfWeek":2,"clickCount_prev2":1230,"totalSignificantAppLaunchCount_prev2":176,"phoneUsageTime_prev2":1271993,"unlockCount_prev2":19,"uniqueAppsLaunched_prev2":29},{"action":true,"timeAppLastUsed":"within half hour","timeOfDay":"afternoon","dayOfWeek":2,"clickCount_prev2":884,"totalSignificantAppLaunchCount_prev2":115,"phoneUsageTime_prev2":994720,"unlockCount_prev2":11,"uniqueAppsLaunched_prev2":20},{"action":true,"timeAppLastUsed":"immediate","timeOfDay":"evening","dayOfWeek":2,"clickCount_prev2":846,"totalSignificantAppLaunchCount_prev2":41,"phoneUsageTime_prev2":607977,"unlockCount_prev2":9,"uniqueAppsLaunched_prev2":20},{"action":false,"timeAppLastUsed":"immediate","timeOfDay":"morning","dayOfWeek":3,"clickCount_prev2":420,"totalSignificantAppLaunchCount_prev2":42,"phoneUsageTime_prev2":189571,"unlockCount_prev2":14,"uniqueAppsLaunched_prev2":16},{"action":false,"timeAppLastUsed":"immediate","timeOfDay":"morning","dayOfWeek":3,"clickCount_prev2":420,"totalSignificantAppLaunchCount_prev2":42,"phoneUsageTime_prev2":189571,"unlockCount_prev2":14,"uniqueAppsLaunched_prev2":16},{"action":true,"timeAppLastUsed":"immediate","timeOfDay":"afternoon","dayOfWeek":3,"clickCount_prev2":1074,"totalSignificantAppLaunchCount_prev2":123,"phoneUsageTime_prev2":823809,"unlockCount_prev2":35,"uniqueAppsLaunched_prev2":23},{"action":true,"timeAppLastUsed":"immediate","timeOfDay":"afternoon","dayOfWeek":3,"clickCount_prev2":670,"totalSignificantAppLaunchCount_prev2":87,"phoneUsageTime_prev2":493091,"unlockCount_prev2":22,"uniqueAppsLaunched_prev2":13},{"action":false,"timeAppLastUsed":"immediate","timeOfDay":"afternoon","dayOfWeek":3,"clickCount_prev2":10,"totalSignificantAppLaunchCount_prev2":0,"phoneUsageTime_prev2":18881,"unlockCount_prev2":3,"uniqueAppsLaunched_prev2":2},{"action":true,"timeAppLastUsed":"within half hour","timeOfDay":"evening","dayOfWeek":3,"clickCount_prev2":314,"totalSignificantAppLaunchCount_prev2":6,"phoneUsageTime_prev2":115326,"unlockCount_prev2":5,"uniqueAppsLaunched_prev2":5},{"action":false,"timeAppLastUsed":"immediate","timeOfDay":"morning","dayOfWeek":4,"clickCount_prev2":672,"totalSignificantAppLaunchCount_prev2":129,"phoneUsageTime_prev2":498700,"unlockCount_prev2":26,"uniqueAppsLaunched_prev2":23},{"action":true,"timeAppLastUsed":"within half hour","timeOfDay":"morning","dayOfWeek":4,"clickCount_prev2":546,"totalSignificantAppLaunchCount_prev2":40,"phoneUsageTime_prev2":335943,"unlockCount_prev2":21,"uniqueAppsLaunched_prev2":18},{"action":true,"timeAppLastUsed":"within half hour","timeOfDay":"morning","dayOfWeek":4,"clickCount_prev2":665,"totalSignificantAppLaunchCount_prev2":38,"phoneUsageTime_prev2":353091,"unlockCount_prev2":14,"uniqueAppsLaunched_prev2":19},{"action":true,"timeAppLastUsed":"immediate","timeOfDay":"afternoon","dayOfWeek":5,"clickCount_prev2":1426,"totalSignificantAppLaunchCount_prev2":147,"phoneUsageTime_prev2":1652798,"unlockCount_prev2":20,"uniqueAppsLaunched_prev2":25},{"action":true,"timeAppLastUsed":"immediate","timeOfDay":"morning","dayOfWeek":6,"clickCount_prev2":510,"totalSignificantAppLaunchCount_prev2":23,"phoneUsageTime_prev2":1087981,"unlockCount_prev2":9,"uniqueAppsLaunched_prev2":14},{"action":true,"timeAppLastUsed":"immediate","timeOfDay":"morning","dayOfWeek":0,"clickCount_prev2":138,"totalSignificantAppLaunchCount_prev2":21,"phoneUsageTime_prev2":116944,"unlockCount_prev2":11,"uniqueAppsLaunched_prev2":12},{"action":true,"timeAppLastUsed":"immediate","timeOfDay":"morning","dayOfWeek":0,"clickCount_prev2":138,"totalSignificantAppLaunchCount_prev2":21,"phoneUsageTime_prev2":116944,"unlockCount_prev2":11,"uniqueAppsLaunched_prev2":12},{"action":true,"timeAppLastUsed":"immediate","timeOfDay":"afternoon","dayOfWeek":0,"clickCount_prev2":892,"totalSignificantAppLaunchCount_prev2":93,"phoneUsageTime_prev2":613110,"unlockCount_prev2":16,"uniqueAppsLaunched_prev2":22},{"action":true,"timeAppLastUsed":"few mins","timeOfDay":"afternoon","dayOfWeek":0,"clickCount_prev2":664,"totalSignificantAppLaunchCount_prev2":115,"phoneUsageTime_prev2":601310,"unlockCount_prev2":13,"uniqueAppsLaunched_prev2":16},{"action":true,"timeAppLastUsed":"immediate","timeOfDay":"morning","dayOfWeek":1,"clickCount_prev2":712,"totalSignificantAppLaunchCount_prev2":30,"phoneUsageTime_prev2":830904,"unlockCount_prev2":10,"uniqueAppsLaunched_prev2":17},{"action":true,"timeAppLastUsed":"immediate","timeOfDay":"morning","dayOfWeek":1,"clickCount_prev2":712,"totalSignificantAppLaunchCount_prev2":30,"phoneUsageTime_prev2":830904,"unlockCount_prev2":10,"uniqueAppsLaunched_prev2":17},{"action":true,"timeAppLastUsed":"within few hours","timeOfDay":"morning","dayOfWeek":1,"clickCount_prev2":288,"totalSignificantAppLaunchCount_prev2":57,"phoneUsageTime_prev2":227191,"unlockCount_prev2":18,"uniqueAppsLaunched_prev2":17},{"action":true,"timeAppLastUsed":"within few hours","timeOfDay":"morning","dayOfWeek":1,"clickCount_prev2":288,"totalSignificantAppLaunchCount_prev2":57,"phoneUsageTime_prev2":227191,"unlockCount_prev2":18,"uniqueAppsLaunched_prev2":17},{"action":true,"timeAppLastUsed":"immediate","timeOfDay":"morning","dayOfWeek":1,"clickCount_prev2":472,"totalSignificantAppLaunchCount_prev2":53,"phoneUsageTime_prev2":404984,"unlockCount_prev2":26,"uniqueAppsLaunched_prev2":17},{"action":false,"timeAppLastUsed":"within half hour","timeOfDay":"morning","dayOfWeek":1,"clickCount_prev2":472,"totalSignificantAppLaunchCount_prev2":53,"phoneUsageTime_prev2":404984,"unlockCount_prev2":26,"uniqueAppsLaunched_prev2":17},{"action":false,"timeAppLastUsed":"immediate","timeOfDay":"morning","dayOfWeek":1,"clickCount_prev2":472,"totalSignificantAppLaunchCount_prev2":53,"phoneUsageTime_prev2":404984,"unlockCount_prev2":26,"uniqueAppsLaunched_prev2":17},{"action":false,"timeAppLastUsed":"immediate","timeOfDay":"morning","dayOfWeek":1,"clickCount_prev2":472,"totalSignificantAppLaunchCount_prev2":53,"phoneUsageTime_prev2":404984,"unlockCount_prev2":26,"uniqueAppsLaunched_prev2":17},{"action":false,"timeAppLastUsed":"immediate","timeOfDay":"morning","dayOfWeek":1,"clickCount_prev2":472,"totalSignificantAppLaunchCount_prev2":53,"phoneUsageTime_prev2":404984,"unlockCount_prev2":26,"uniqueAppsLaunched_prev2":17},{"action":true,"timeAppLastUsed":"immediate","timeOfDay":"morning","dayOfWeek":1,"clickCount_prev2":472,"totalSignificantAppLaunchCount_prev2":53,"phoneUsageTime_prev2":404984,"unlockCount_prev2":26,"uniqueAppsLaunched_prev2":17},{"action":true,"timeAppLastUsed":"immediate","timeOfDay":"morning","dayOfWeek":1,"clickCount_prev2":472,"totalSignificantAppLaunchCount_prev2":53,"phoneUsageTime_prev2":404984,"unlockCount_prev2":26,"uniqueAppsLaunched_prev2":17},{"action":true,"timeAppLastUsed":"within few hours","timeOfDay":"morning","dayOfWeek":2,"clickCount_prev2":184,"totalSignificantAppLaunchCount_prev2":51,"phoneUsageTime_prev2":243057,"unlockCount_prev2":16,"uniqueAppsLaunched_prev2":18},{"action":true,"timeAppLastUsed":"immediate","timeOfDay":"morning","dayOfWeek":2,"clickCount_prev2":184,"totalSignificantAppLaunchCount_prev2":51,"phoneUsageTime_prev2":243057,"unlockCount_prev2":16,"uniqueAppsLaunched_prev2":18},{"action":true,"timeAppLastUsed":"immediate","timeOfDay":"morning","dayOfWeek":2,"clickCount_prev2":184,"totalSignificantAppLaunchCount_prev2":51,"phoneUsageTime_prev2":243057,"unlockCount_prev2":16,"uniqueAppsLaunched_prev2":18},{"action":true,"timeAppLastUsed":"within 24 hours","timeOfDay":"morning","dayOfWeek":6,"clickCount_prev2":491,"totalSignificantAppLaunchCount_prev2":62,"phoneUsageTime_prev2":1279346,"unlockCount_prev2":18,"uniqueAppsLaunched_prev2":22},{"action":true,"timeAppLastUsed":"within 24 hours","timeOfDay":"morning","dayOfWeek":6,"clickCount_prev2":491,"totalSignificantAppLaunchCount_prev2":62,"phoneUsageTime_prev2":1279346,"unlockCount_prev2":18,"uniqueAppsLaunched_prev2":22},{"action":false,"timeAppLastUsed":"within 24 hours","timeOfDay":"morning","dayOfWeek":0,"clickCount_prev2":82,"totalSignificantAppLaunchCount_prev2":13,"phoneUsageTime_prev2":64844,"unlockCount_prev2":7,"uniqueAppsLaunched_prev2":8},{"action":false,"timeAppLastUsed":"within 24 hours","timeOfDay":"morning","dayOfWeek":0,"clickCount_prev2":82,"totalSignificantAppLaunchCount_prev2":13,"phoneUsageTime_prev2":64844,"unlockCount_prev2":7,"uniqueAppsLaunched_prev2":8},{"action":true,"timeAppLastUsed":"immediate","timeOfDay":"evening","dayOfWeek":0,"clickCount_prev2":234,"totalSignificantAppLaunchCount_prev2":12,"phoneUsageTime_prev2":188065,"unlockCount_prev2":8,"uniqueAppsLaunched_prev2":7},{"action":true,"timeAppLastUsed":"immediate","timeOfDay":"night","dayOfWeek":1,"clickCount_prev2":879,"totalSignificantAppLaunchCount_prev2":30,"phoneUsageTime_prev2":621064,"unlockCount_prev2":3,"uniqueAppsLaunched_prev2":14},{"action":true,"timeAppLastUsed":"immediate","timeOfDay":"night","dayOfWeek":1,"clickCount_prev2":879,"totalSignificantAppLaunchCount_prev2":30,"phoneUsageTime_prev2":621064,"unlockCount_prev2":3,"uniqueAppsLaunched_prev2":14},{"action":true,"timeAppLastUsed":"immediate","timeOfDay":"evening","dayOfWeek":2,"clickCount_prev2":4820,"totalSignificantAppLaunchCount_prev2":83,"phoneUsageTime_prev2":1692382,"unlockCount_prev2":13,"uniqueAppsLaunched_prev2":19},{"action":true,"timeAppLastUsed":"immediate","timeOfDay":"evening","dayOfWeek":2,"clickCount_prev2":4820,"totalSignificantAppLaunchCount_prev2":83,"phoneUsageTime_prev2":1692382,"unlockCount_prev2":13,"uniqueAppsLaunched_prev2":19},{"action":true,"timeAppLastUsed":"immediate","timeOfDay":"evening","dayOfWeek":2,"clickCount_prev2":3052,"totalSignificantAppLaunchCount_prev2":83,"phoneUsageTime_prev2":1077635,"unlockCount_prev2":17,"uniqueAppsLaunched_prev2":16},{"action":true,"timeAppLastUsed":"immediate","timeOfDay":"evening","dayOfWeek":2,"clickCount_prev2":3052,"totalSignificantAppLaunchCount_prev2":83,"phoneUsageTime_prev2":1077635,"unlockCount_prev2":17,"uniqueAppsLaunched_prev2":16},{"action":true,"timeAppLastUsed":"immediate","timeOfDay":"evening","dayOfWeek":2,"clickCount_prev2":1540,"totalSignificantAppLaunchCount_prev2":57,"phoneUsageTime_prev2":577166,"unlockCount_prev2":10,"uniqueAppsLaunched_prev2":8},{"action":true,"timeAppLastUsed":"immediate","timeOfDay":"afternoon","dayOfWeek":3,"clickCount_prev2":352,"totalSignificantAppLaunchCount_prev2":34,"phoneUsageTime_prev2":314707,"unlockCount_prev2":10,"uniqueAppsLaunched_prev2":11},{"action":true,"timeAppLastUsed":"within half hour","timeOfDay":"afternoon","dayOfWeek":3,"clickCount_prev2":352,"totalSignificantAppLaunchCount_prev2":34,"phoneUsageTime_prev2":314707,"unlockCount_prev2":10,"uniqueAppsLaunched_prev2":11},{"action":true,"timeAppLastUsed":"within 24 hours","timeOfDay":"morning","dayOfWeek":4,"clickCount_prev2":248,"totalSignificantAppLaunchCount_prev2":7,"phoneUsageTime_prev2":56974,"unlockCount_prev2":8,"uniqueAppsLaunched_prev2":10},{"action":false,"timeAppLastUsed":"immediate","timeOfDay":"afternoon","dayOfWeek":4,"clickCount_prev2":334,"totalSignificantAppLaunchCount_prev2":56,"phoneUsageTime_prev2":264748,"unlockCount_prev2":19,"uniqueAppsLaunched_prev2":13},{"action":false,"timeAppLastUsed":"within half hour","timeOfDay":"afternoon","dayOfWeek":4,"clickCount_prev2":334,"totalSignificantAppLaunchCount_prev2":56,"phoneUsageTime_prev2":264748,"unlockCount_prev2":19,"uniqueAppsLaunched_prev2":13},{"action":true,"timeAppLastUsed":"immediate","timeOfDay":"afternoon","dayOfWeek":4,"clickCount_prev2":334,"totalSignificantAppLaunchCount_prev2":56,"phoneUsageTime_prev2":264748,"unlockCount_prev2":19,"uniqueAppsLaunched_prev2":13},{"action":true,"timeAppLastUsed":"immediate","timeOfDay":"afternoon","dayOfWeek":4,"clickCount_prev2":763,"totalSignificantAppLaunchCount_prev2":55,"phoneUsageTime_prev2":391353,"unlockCount_prev2":20,"uniqueAppsLaunched_prev2":13},{"action":true,"timeAppLastUsed":"immediate","timeOfDay":"afternoon","dayOfWeek":4,"clickCount_prev2":763,"totalSignificantAppLaunchCount_prev2":55,"phoneUsageTime_prev2":391353,"unlockCount_prev2":20,"uniqueAppsLaunched_prev2":13},{"action":true,"timeAppLastUsed":"few mins","timeOfDay":"evening","dayOfWeek":4,"clickCount_prev2":252,"totalSignificantAppLaunchCount_prev2":38,"phoneUsageTime_prev2":213335,"unlockCount_prev2":18,"uniqueAppsLaunched_prev2":9},{"action":true,"timeAppLastUsed":"few mins","timeOfDay":"evening","dayOfWeek":4,"clickCount_prev2":252,"totalSignificantAppLaunchCount_prev2":38,"phoneUsageTime_prev2":213335,"unlockCount_prev2":18,"uniqueAppsLaunched_prev2":9},{"action":false,"timeAppLastUsed":"immediate","timeOfDay":"evening","dayOfWeek":4,"clickCount_prev2":476,"totalSignificantAppLaunchCount_prev2":16,"phoneUsageTime_prev2":294015,"unlockCount_prev2":12,"uniqueAppsLaunched_prev2":6},{"action":true,"timeAppLastUsed":"within 24 hours","timeOfDay":"morning","dayOfWeek":5,"clickCount_prev2":566,"totalSignificantAppLaunchCount_prev2":16,"phoneUsageTime_prev2":713557,"unlockCount_prev2":1,"uniqueAppsLaunched_prev2":7},{"action":true,"timeAppLastUsed":"immediate","timeOfDay":"morning","dayOfWeek":5,"clickCount_prev2":2374,"totalSignificantAppLaunchCount_prev2":56,"phoneUsageTime_prev2":1713456,"unlockCount_prev2":8,"uniqueAppsLaunched_prev2":17},{"action":true,"timeAppLastUsed":"immediate","timeOfDay":"morning","dayOfWeek":5,"clickCount_prev2":2302,"totalSignificantAppLaunchCount_prev2":91,"phoneUsageTime_prev2":1653101,"unlockCount_prev2":18,"uniqueAppsLaunched_prev2":22},{"action":false,"timeAppLastUsed":"within 24 hours","timeOfDay":"afternoon","dayOfWeek":6,"clickCount_prev2":634,"totalSignificantAppLaunchCount_prev2":14,"phoneUsageTime_prev2":358160,"unlockCount_prev2":13,"uniqueAppsLaunched_prev2":13},{"action":true,"timeAppLastUsed":"within 24 hours","timeOfDay":"morning","dayOfWeek":5,"clickCount_prev2":538,"totalSignificantAppLaunchCount_prev2":82,"phoneUsageTime_prev2":520520,"unlockCount_prev2":11,"uniqueAppsLaunched_prev2":17},{"action":true,"timeAppLastUsed":"immediate","timeOfDay":"morning","dayOfWeek":5,"clickCount_prev2":538,"totalSignificantAppLaunchCount_prev2":82,"phoneUsageTime_prev2":520520,"unlockCount_prev2":11,"uniqueAppsLaunched_prev2":17},{"action":false,"timeAppLastUsed":"immediate","timeOfDay":"afternoon","dayOfWeek":5,"clickCount_prev2":924,"totalSignificantAppLaunchCount_prev2":85,"phoneUsageTime_prev2":642294,"unlockCount_prev2":25,"uniqueAppsLaunched_prev2":19},{"action":false,"timeAppLastUsed":"immediate","timeOfDay":"afternoon","dayOfWeek":5,"clickCount_prev2":812,"totalSignificantAppLaunchCount_prev2":94,"phoneUsageTime_prev2":607295,"unlockCount_prev2":28,"uniqueAppsLaunched_prev2":21},{"action":false,"timeAppLastUsed":"within hour","timeOfDay":"evening","dayOfWeek":5,"clickCount_prev2":402,"totalSignificantAppLaunchCount_prev2":73,"phoneUsageTime_prev2":422050,"unlockCount_prev2":19,"uniqueAppsLaunched_prev2":17},{"action":true,"timeAppLastUsed":"immediate","timeOfDay":"evening","dayOfWeek":5,"clickCount_prev2":402,"totalSignificantAppLaunchCount_prev2":73,"phoneUsageTime_prev2":422050,"unlockCount_prev2":19,"uniqueAppsLaunched_prev2":17},{"action":false,"timeAppLastUsed":"immediate","timeOfDay":"evening","dayOfWeek":6,"clickCount_prev2":629,"totalSignificantAppLaunchCount_prev2":69,"phoneUsageTime_prev2":960944,"unlockCount_prev2":11,"uniqueAppsLaunched_prev2":20},{"action":true,"timeAppLastUsed":"immediate","timeOfDay":"evening","dayOfWeek":6,"clickCount_prev2":47,"totalSignificantAppLaunchCount_prev2":21,"phoneUsageTime_prev2":50729,"unlockCount_prev2":4,"uniqueAppsLaunched_prev2":7},{"action":false,"timeAppLastUsed":"within last week","timeOfDay":"morning","dayOfWeek":0,"clickCount_prev2":242,"totalSignificantAppLaunchCount_prev2":54,"phoneUsageTime_prev2":251438,"unlockCount_prev2":9,"uniqueAppsLaunched_prev2":10},{"action":false,"timeAppLastUsed":"within last week","timeOfDay":"morning","dayOfWeek":0,"clickCount_prev2":242,"totalSignificantAppLaunchCount_prev2":54,"phoneUsageTime_prev2":251438,"unlockCount_prev2":9,"uniqueAppsLaunched_prev2":10},{"action":true,"timeAppLastUsed":"immediate","timeOfDay":"morning","dayOfWeek":0,"clickCount_prev2":216,"totalSignificantAppLaunchCount_prev2":26,"phoneUsageTime_prev2":255490,"unlockCount_prev2":18,"uniqueAppsLaunched_prev2":18},{"action":true,"timeAppLastUsed":"immediate","timeOfDay":"morning","dayOfWeek":0,"clickCount_prev2":216,"totalSignificantAppLaunchCount_prev2":26,"phoneUsageTime_prev2":255490,"unlockCount_prev2":18,"uniqueAppsLaunched_prev2":18},{"action":true,"timeAppLastUsed":"immediate","timeOfDay":"morning","dayOfWeek":0,"clickCount_prev2":182,"totalSignificantAppLaunchCount_prev2":32,"phoneUsageTime_prev2":267578,"unlockCount_prev2":23,"uniqueAppsLaunched_prev2":21},{"action":true,"timeAppLastUsed":"immediate","timeOfDay":"morning","dayOfWeek":0,"clickCount_prev2":182,"totalSignificantAppLaunchCount_prev2":32,"phoneUsageTime_prev2":267578,"unlockCount_prev2":23,"uniqueAppsLaunched_prev2":21},{"action":true,"timeAppLastUsed":"immediate","timeOfDay":"morning","dayOfWeek":0,"clickCount_prev2":182,"totalSignificantAppLaunchCount_prev2":32,"phoneUsageTime_prev2":267578,"unlockCount_prev2":23,"uniqueAppsLaunched_prev2":21},{"action":true,"timeAppLastUsed":"immediate","timeOfDay":"morning","dayOfWeek":0,"clickCount_prev2":182,"totalSignificantAppLaunchCount_prev2":32,"phoneUsageTime_prev2":267578,"unlockCount_prev2":23,"uniqueAppsLaunched_prev2":21},{"action":true,"timeAppLastUsed":"immediate","timeOfDay":"afternoon","dayOfWeek":0,"clickCount_prev2":200,"totalSignificantAppLaunchCount_prev2":70,"phoneUsageTime_prev2":438028,"unlockCount_prev2":14,"uniqueAppsLaunched_prev2":15},{"action":false,"timeAppLastUsed":"immediate","timeOfDay":"afternoon","dayOfWeek":0,"clickCount_prev2":65,"totalSignificantAppLaunchCount_prev2":12,"phoneUsageTime_prev2":104212,"unlockCount_prev2":7,"uniqueAppsLaunched_prev2":7},{"action":false,"timeAppLastUsed":"within half hour","timeOfDay":"evening","dayOfWeek":0,"clickCount_prev2":363,"totalSignificantAppLaunchCount_prev2":75,"phoneUsageTime_prev2":630384,"unlockCount_prev2":13,"uniqueAppsLaunched_prev2":18},{"action":false,"timeAppLastUsed":"immediate","timeOfDay":"afternoon","dayOfWeek":1,"clickCount_prev2":287,"totalSignificantAppLaunchCount_prev2":71,"phoneUsageTime_prev2":481305,"unlockCount_prev2":20,"uniqueAppsLaunched_prev2":14},{"action":true,"timeAppLastUsed":"immediate","timeOfDay":"afternoon","dayOfWeek":1,"clickCount_prev2":414,"totalSignificantAppLaunchCount_prev2":79,"phoneUsageTime_prev2":610370,"unlockCount_prev2":16,"uniqueAppsLaunched_prev2":16},{"action":true,"timeAppLastUsed":"immediate","timeOfDay":"evening","dayOfWeek":1,"clickCount_prev2":311,"totalSignificantAppLaunchCount_prev2":93,"phoneUsageTime_prev2":533010,"unlockCount_prev2":12,"uniqueAppsLaunched_prev2":12},{"action":true,"timeAppLastUsed":"few mins","timeOfDay":"evening","dayOfWeek":1,"clickCount_prev2":311,"totalSignificantAppLaunchCount_prev2":93,"phoneUsageTime_prev2":533010,"unlockCount_prev2":12,"uniqueAppsLaunched_prev2":12},{"action":true,"timeAppLastUsed":"immediate","timeOfDay":"evening","dayOfWeek":1,"clickCount_prev2":303,"totalSignificantAppLaunchCount_prev2":123,"phoneUsageTime_prev2":556292,"unlockCount_prev2":13,"uniqueAppsLaunched_prev2":13},{"action":false,"timeAppLastUsed":"immediate","timeOfDay":"morning","dayOfWeek":2,"clickCount_prev2":530,"totalSignificantAppLaunchCount_prev2":70,"phoneUsageTime_prev2":683743,"unlockCount_prev2":18,"uniqueAppsLaunched_prev2":16},{"action":true,"timeAppLastUsed":"within half hour","timeOfDay":"morning","dayOfWeek":2,"clickCount_prev2":530,"totalSignificantAppLaunchCount_prev2":70,"phoneUsageTime_prev2":683743,"unlockCount_prev2":18,"uniqueAppsLaunched_prev2":16},{"action":true,"timeAppLastUsed":"immediate","timeOfDay":"morning","dayOfWeek":2,"clickCount_prev2":530,"totalSignificantAppLaunchCount_prev2":70,"phoneUsageTime_prev2":683743,"unlockCount_prev2":18,"uniqueAppsLaunched_prev2":16},{"action":true,"timeAppLastUsed":"immediate","timeOfDay":"morning","dayOfWeek":2,"clickCount_prev2":478,"totalSignificantAppLaunchCount_prev2":72,"phoneUsageTime_prev2":710978,"unlockCount_prev2":16,"uniqueAppsLaunched_prev2":16},{"action":true,"timeAppLastUsed":"few mins","timeOfDay":"morning","dayOfWeek":2,"clickCount_prev2":478,"totalSignificantAppLaunchCount_prev2":72,"phoneUsageTime_prev2":710978,"unlockCount_prev2":16,"uniqueAppsLaunched_prev2":16},{"action":false,"timeAppLastUsed":"immediate","timeOfDay":"afternoon","dayOfWeek":3,"clickCount_prev2":587,"totalSignificantAppLaunchCount_prev2":99,"phoneUsageTime_prev2":789804,"unlockCount_prev2":19,"uniqueAppsLaunched_prev2":12},{"action":false,"timeAppLastUsed":"immediate","timeOfDay":"afternoon","dayOfWeek":3,"clickCount_prev2":587,"totalSignificantAppLaunchCount_prev2":99,"phoneUsageTime_prev2":789804,"unlockCount_prev2":19,"uniqueAppsLaunched_prev2":12},{"action":true,"timeAppLastUsed":"within hour","timeOfDay":"afternoon","dayOfWeek":3,"clickCount_prev2":182,"totalSignificantAppLaunchCount_prev2":44,"phoneUsageTime_prev2":267860,"unlockCount_prev2":8,"uniqueAppsLaunched_prev2":12},{"action":true,"timeAppLastUsed":"immediate","timeOfDay":"evening","dayOfWeek":3,"clickCount_prev2":378,"totalSignificantAppLaunchCount_prev2":40,"phoneUsageTime_prev2":439387,"unlockCount_prev2":9,"uniqueAppsLaunched_prev2":9},{"action":true,"timeAppLastUsed":"immediate","timeOfDay":"evening","dayOfWeek":3,"clickCount_prev2":378,"totalSignificantAppLaunchCount_prev2":40,"phoneUsageTime_prev2":439387,"unlockCount_prev2":9,"uniqueAppsLaunched_prev2":9},{"action":true,"timeAppLastUsed":"immediate","timeOfDay":"night","dayOfWeek":3,"clickCount_prev2":378,"totalSignificantAppLaunchCount_prev2":40,"phoneUsageTime_prev2":439387,"unlockCount_prev2":9,"uniqueAppsLaunched_prev2":9},{"action":false,"timeAppLastUsed":"immediate","timeOfDay":"evening","dayOfWeek":5,"clickCount_prev2":792,"totalSignificantAppLaunchCount_prev2":76,"phoneUsageTime_prev2":459616,"unlockCount_prev2":20,"uniqueAppsLaunched_prev2":18},{"action":false,"timeAppLastUsed":"within half hour","timeOfDay":"afternoon","dayOfWeek":6,"clickCount_prev2":158,"totalSignificantAppLaunchCount_prev2":45,"phoneUsageTime_prev2":253851,"unlockCount_prev2":8,"uniqueAppsLaunched_prev2":9},{"action":true,"timeAppLastUsed":"within 24 hours","timeOfDay":"afternoon","dayOfWeek":6,"clickCount_prev2":94,"totalSignificantAppLaunchCount_prev2":36,"phoneUsageTime_prev2":202264,"unlockCount_prev2":5,"uniqueAppsLaunched_prev2":9},{"action":true,"timeAppLastUsed":"immediate","timeOfDay":"morning","dayOfWeek":5,"clickCount_prev2":567,"totalSignificantAppLaunchCount_prev2":76,"phoneUsageTime_prev2":1033634,"unlockCount_prev2":20,"uniqueAppsLaunched_prev2":15},{"action":true,"timeAppLastUsed":"immediate","timeOfDay":"morning","dayOfWeek":5,"clickCount_prev2":521,"totalSignificantAppLaunchCount_prev2":75,"phoneUsageTime_prev2":894103,"unlockCount_prev2":20,"uniqueAppsLaunched_prev2":10},{"action":true,"timeAppLastUsed":"immediate","timeOfDay":"morning","dayOfWeek":5,"clickCount_prev2":521,"totalSignificantAppLaunchCount_prev2":75,"phoneUsageTime_prev2":894103,"unlockCount_prev2":20,"uniqueAppsLaunched_prev2":10},{"action":true,"timeAppLastUsed":"immediate","timeOfDay":"morning","dayOfWeek":5,"clickCount_prev2":521,"totalSignificantAppLaunchCount_prev2":75,"phoneUsageTime_prev2":894103,"unlockCount_prev2":20,"uniqueAppsLaunched_prev2":10},{"action":true,"timeAppLastUsed":"immediate","timeOfDay":"morning","dayOfWeek":5,"clickCount_prev2":521,"totalSignificantAppLaunchCount_prev2":75,"phoneUsageTime_prev2":894103,"unlockCount_prev2":20,"uniqueAppsLaunched_prev2":10},{"action":true,"timeAppLastUsed":"within half hour","timeOfDay":"morning","dayOfWeek":5,"clickCount_prev2":575,"totalSignificantAppLaunchCount_prev2":37,"phoneUsageTime_prev2":451729,"unlockCount_prev2":12,"uniqueAppsLaunched_prev2":6},{"action":true,"timeAppLastUsed":"immediate","timeOfDay":"morning","dayOfWeek":5,"clickCount_prev2":668,"totalSignificantAppLaunchCount_prev2":31,"phoneUsageTime_prev2":449249,"unlockCount_prev2":8,"uniqueAppsLaunched_prev2":8},{"action":true,"timeAppLastUsed":"immediate","timeOfDay":"afternoon","dayOfWeek":5,"clickCount_prev2":278,"totalSignificantAppLaunchCount_prev2":34,"phoneUsageTime_prev2":394421,"unlockCount_prev2":10,"uniqueAppsLaunched_prev2":12},{"action":true,"timeAppLastUsed":"immediate","timeOfDay":"afternoon","dayOfWeek":5,"clickCount_prev2":503,"totalSignificantAppLaunchCount_prev2":125,"phoneUsageTime_prev2":803467,"unlockCount_prev2":23,"uniqueAppsLaunched_prev2":22},{"action":true,"timeAppLastUsed":"immediate","timeOfDay":"afternoon","dayOfWeek":5,"clickCount_prev2":503,"totalSignificantAppLaunchCount_prev2":125,"phoneUsageTime_prev2":803467,"unlockCount_prev2":23,"uniqueAppsLaunched_prev2":22},{"action":false,"timeAppLastUsed":"immediate","timeOfDay":"afternoon","dayOfWeek":5,"clickCount_prev2":503,"totalSignificantAppLaunchCount_prev2":125,"phoneUsageTime_prev2":803467,"unlockCount_prev2":23,"uniqueAppsLaunched_prev2":22},{"action":true,"timeAppLastUsed":"within half hour","timeOfDay":"afternoon","dayOfWeek":5,"clickCount_prev2":854,"totalSignificantAppLaunchCount_prev2":93,"phoneUsageTime_prev2":1055089,"unlockCount_prev2":21,"uniqueAppsLaunched_prev2":18},{"action":false,"timeAppLastUsed":"immediate","timeOfDay":"afternoon","dayOfWeek":5,"clickCount_prev2":854,"totalSignificantAppLaunchCount_prev2":93,"phoneUsageTime_prev2":1055089,"unlockCount_prev2":21,"uniqueAppsLaunched_prev2":18},{"action":false,"timeAppLastUsed":"immediate","timeOfDay":"afternoon","dayOfWeek":5,"clickCount_prev2":854,"totalSignificantAppLaunchCount_prev2":93,"phoneUsageTime_prev2":1055089,"unlockCount_prev2":21,"uniqueAppsLaunched_prev2":18},{"action":false,"timeAppLastUsed":"immediate","timeOfDay":"afternoon","dayOfWeek":5,"clickCount_prev2":854,"totalSignificantAppLaunchCount_prev2":93,"phoneUsageTime_prev2":1055089,"unlockCount_prev2":21,"uniqueAppsLaunched_prev2":18},{"action":true,"timeAppLastUsed":"immediate","timeOfDay":"evening","dayOfWeek":5,"clickCount_prev2":854,"totalSignificantAppLaunchCount_prev2":93,"phoneUsageTime_prev2":1055089,"unlockCount_prev2":21,"uniqueAppsLaunched_prev2":18},{"action":true,"timeAppLastUsed":"within half hour","timeOfDay":"evening","dayOfWeek":5,"clickCount_prev2":602,"totalSignificantAppLaunchCount_prev2":75,"phoneUsageTime_prev2":886928,"unlockCount_prev2":23,"uniqueAppsLaunched_prev2":21},{"action":false,"timeAppLastUsed":"immediate","timeOfDay":"evening","dayOfWeek":5,"clickCount_prev2":602,"totalSignificantAppLaunchCount_prev2":75,"phoneUsageTime_prev2":886928,"unlockCount_prev2":23,"uniqueAppsLaunched_prev2":21},{"action":false,"timeAppLastUsed":"immediate","timeOfDay":"evening","dayOfWeek":5,"clickCount_prev2":602,"totalSignificantAppLaunchCount_prev2":75,"phoneUsageTime_prev2":886928,"unlockCount_prev2":23,"uniqueAppsLaunched_prev2":21},{"action":true,"timeAppLastUsed":"immediate","timeOfDay":"evening","dayOfWeek":5,"clickCount_prev2":139,"totalSignificantAppLaunchCount_prev2":32,"phoneUsageTime_prev2":300651,"unlockCount_prev2":17,"uniqueAppsLaunched_prev2":15},{"action":true,"timeAppLastUsed":"immediate","timeOfDay":"evening","dayOfWeek":5,"clickCount_prev2":139,"totalSignificantAppLaunchCount_prev2":32,"phoneUsageTime_prev2":300651,"unlockCount_prev2":17,"uniqueAppsLaunched_prev2":15},{"action":true,"timeAppLastUsed":"immediate","timeOfDay":"evening","dayOfWeek":5,"clickCount_prev2":139,"totalSignificantAppLaunchCount_prev2":32,"phoneUsageTime_prev2":300651,"unlockCount_prev2":17,"uniqueAppsLaunched_prev2":15},{"action":true,"timeAppLastUsed":"immediate","timeOfDay":"evening","dayOfWeek":5,"clickCount_prev2":139,"totalSignificantAppLaunchCount_prev2":32,"phoneUsageTime_prev2":300651,"unlockCount_prev2":17,"uniqueAppsLaunched_prev2":15},{"action":true,"timeAppLastUsed":"few mins","timeOfDay":"evening","dayOfWeek":5,"clickCount_prev2":70,"totalSignificantAppLaunchCount_prev2":10,"phoneUsageTime_prev2":172785,"unlockCount_prev2":7,"uniqueAppsLaunched_prev2":8},{"action":true,"timeAppLastUsed":"within 24 hours","timeOfDay":"morning","dayOfWeek":6,"clickCount_prev2":162,"totalSignificantAppLaunchCount_prev2":20,"phoneUsageTime_prev2":589599,"unlockCount_prev2":4,"uniqueAppsLaunched_prev2":6},{"action":true,"timeAppLastUsed":"immediate","timeOfDay":"afternoon","dayOfWeek":6,"clickCount_prev2":611,"totalSignificantAppLaunchCount_prev2":43,"phoneUsageTime_prev2":958395,"unlockCount_prev2":13,"uniqueAppsLaunched_prev2":8},{"action":true,"timeAppLastUsed":"immediate","timeOfDay":"morning","dayOfWeek":0,"clickCount_prev2":2018,"totalSignificantAppLaunchCount_prev2":126,"phoneUsageTime_prev2":1374348,"unlockCount_prev2":20,"uniqueAppsLaunched_prev2":24},{"action":true,"timeAppLastUsed":"immediate","timeOfDay":"morning","dayOfWeek":0,"clickCount_prev2":2018,"totalSignificantAppLaunchCount_prev2":126,"phoneUsageTime_prev2":1374348,"unlockCount_prev2":20,"uniqueAppsLaunched_prev2":24},{"action":true,"timeAppLastUsed":"immediate","timeOfDay":"afternoon","dayOfWeek":0,"clickCount_prev2":400,"totalSignificantAppLaunchCount_prev2":65,"phoneUsageTime_prev2":410894,"unlockCount_prev2":16,"uniqueAppsLaunched_prev2":17},{"action":true,"timeAppLastUsed":"immediate","timeOfDay":"afternoon","dayOfWeek":0,"clickCount_prev2":400,"totalSignificantAppLaunchCount_prev2":65,"phoneUsageTime_prev2":410894,"unlockCount_prev2":16,"uniqueAppsLaunched_prev2":17},{"action":true,"timeAppLastUsed":"immediate","timeOfDay":"afternoon","dayOfWeek":0,"clickCount_prev2":400,"totalSignificantAppLaunchCount_prev2":65,"phoneUsageTime_prev2":410894,"unlockCount_prev2":16,"uniqueAppsLaunched_prev2":17},{"action":true,"timeAppLastUsed":"immediate","timeOfDay":"evening","dayOfWeek":0,"clickCount_prev2":2444,"totalSignificantAppLaunchCount_prev2":84,"phoneUsageTime_prev2":2579379,"unlockCount_prev2":25,"uniqueAppsLaunched_prev2":16},{"action":true,"timeAppLastUsed":"immediate","timeOfDay":"morning","dayOfWeek":1,"clickCount_prev2":242,"totalSignificantAppLaunchCount_prev2":22,"phoneUsageTime_prev2":228716,"unlockCount_prev2":9,"uniqueAppsLaunched_prev2":11},{"action":true,"timeAppLastUsed":"immediate","timeOfDay":"morning","dayOfWeek":1,"clickCount_prev2":242,"totalSignificantAppLaunchCount_prev2":22,"phoneUsageTime_prev2":228716,"unlockCount_prev2":9,"uniqueAppsLaunched_prev2":11},{"action":false,"timeAppLastUsed":"immediate","timeOfDay":"morning","dayOfWeek":1,"clickCount_prev2":124,"totalSignificantAppLaunchCount_prev2":6,"phoneUsageTime_prev2":170730,"unlockCount_prev2":14,"uniqueAppsLaunched_prev2":5},{"action":true,"timeAppLastUsed":"few mins","timeOfDay":"morning","dayOfWeek":1,"clickCount_prev2":380,"totalSignificantAppLaunchCount_prev2":27,"phoneUsageTime_prev2":312809,"unlockCount_prev2":12,"uniqueAppsLaunched_prev2":11},{"action":true,"timeAppLastUsed":"within hour","timeOfDay":"afternoon","dayOfWeek":1,"clickCount_prev2":1990,"totalSignificantAppLaunchCount_prev2":78,"phoneUsageTime_prev2":1440948,"unlockCount_prev2":13,"uniqueAppsLaunched_prev2":21},{"action":true,"timeAppLastUsed":"immediate","timeOfDay":"evening","dayOfWeek":1,"clickCount_prev2":1980,"totalSignificantAppLaunchCount_prev2":83,"phoneUsageTime_prev2":1383278,"unlockCount_prev2":9,"uniqueAppsLaunched_prev2":17},{"action":true,"timeAppLastUsed":"within few hours","timeOfDay":"evening","dayOfWeek":1,"clickCount_prev2":350,"totalSignificantAppLaunchCount_prev2":19,"phoneUsageTime_prev2":522343,"unlockCount_prev2":6,"uniqueAppsLaunched_prev2":12},{"action":false,"timeAppLastUsed":"immediate","timeOfDay":"morning","dayOfWeek":2,"clickCount_prev2":1012,"totalSignificantAppLaunchCount_prev2":56,"phoneUsageTime_prev2":674905,"unlockCount_prev2":7,"uniqueAppsLaunched_prev2":13},{"action":false,"timeAppLastUsed":"immediate","timeOfDay":"morning","dayOfWeek":2,"clickCount_prev2":1012,"totalSignificantAppLaunchCount_prev2":56,"phoneUsageTime_prev2":674905,"unlockCount_prev2":7,"uniqueAppsLaunched_prev2":13},{"action":true,"timeAppLastUsed":"within hour","timeOfDay":"afternoon","dayOfWeek":2,"clickCount_prev2":136,"totalSignificantAppLaunchCount_prev2":13,"phoneUsageTime_prev2":77671,"unlockCount_prev2":5,"uniqueAppsLaunched_prev2":6},{"action":true,"timeAppLastUsed":"immediate","timeOfDay":"early-morning","dayOfWeek":3,"clickCount_prev2":740,"totalSignificantAppLaunchCount_prev2":43,"phoneUsageTime_prev2":412343,"unlockCount_prev2":10,"uniqueAppsLaunched_prev2":12},{"action":false,"timeAppLastUsed":"within last week","timeOfDay":"morning","dayOfWeek":3,"clickCount_prev2":70,"totalSignificantAppLaunchCount_prev2":3,"phoneUsageTime_prev2":50424,"unlockCount_prev2":3,"uniqueAppsLaunched_prev2":3},{"action":true,"timeAppLastUsed":"within few hours","timeOfDay":"afternoon","dayOfWeek":3,"clickCount_prev2":224,"totalSignificantAppLaunchCount_prev2":17,"phoneUsageTime_prev2":127859,"unlockCount_prev2":9,"uniqueAppsLaunched_prev2":12},{"action":true,"timeAppLastUsed":"within last week","timeOfDay":"afternoon","dayOfWeek":3,"clickCount_prev2":102,"totalSignificantAppLaunchCount_prev2":12,"phoneUsageTime_prev2":89698,"unlockCount_prev2":4,"uniqueAppsLaunched_prev2":7},{"action":true,"timeAppLastUsed":"within hour","timeOfDay":"evening","dayOfWeek":4,"clickCount_prev2":1229,"totalSignificantAppLaunchCount_prev2":112,"phoneUsageTime_prev2":1443807,"unlockCount_prev2":16,"uniqueAppsLaunched_prev2":17},{"action":true,"timeAppLastUsed":"immediate","timeOfDay":"evening","dayOfWeek":4,"clickCount_prev2":441,"totalSignificantAppLaunchCount_prev2":89,"phoneUsageTime_prev2":552233,"unlockCount_prev2":14,"uniqueAppsLaunched_prev2":13},{"action":true,"timeAppLastUsed":"within 24 hours","timeOfDay":"night","dayOfWeek":4,"clickCount_prev2":821,"totalSignificantAppLaunchCount_prev2":74,"phoneUsageTime_prev2":1302842,"unlockCount_prev2":9,"uniqueAppsLaunched_prev2":13},{"action":true,"timeAppLastUsed":"within 24 hours","timeOfDay":"night","dayOfWeek":4,"clickCount_prev2":821,"totalSignificantAppLaunchCount_prev2":74,"phoneUsageTime_prev2":1302842,"unlockCount_prev2":9,"uniqueAppsLaunched_prev2":13},{"action":true,"timeAppLastUsed":"immediate","timeOfDay":"evening","dayOfWeek":5,"clickCount_prev2":1167,"totalSignificantAppLaunchCount_prev2":103,"phoneUsageTime_prev2":1509352,"unlockCount_prev2":10,"uniqueAppsLaunched_prev2":29},{"action":false,"timeAppLastUsed":"immediate","timeOfDay":"evening","dayOfWeek":5,"clickCount_prev2":1098,"totalSignificantAppLaunchCount_prev2":77,"phoneUsageTime_prev2":1427034,"unlockCount_prev2":9,"uniqueAppsLaunched_prev2":22},{"action":true,"timeAppLastUsed":"within last week","timeOfDay":"evening","dayOfWeek":5,"clickCount_prev2":624,"totalSignificantAppLaunchCount_prev2":61,"phoneUsageTime_prev2":1056200,"unlockCount_prev2":12,"uniqueAppsLaunched_prev2":17},{"action":true,"timeAppLastUsed":"immediate","timeOfDay":"evening","dayOfWeek":5,"clickCount_prev2":912,"totalSignificantAppLaunchCount_prev2":66,"phoneUsageTime_prev2":1479699,"unlockCount_prev2":26,"uniqueAppsLaunched_prev2":14},{"action":true,"timeAppLastUsed":"immediate","timeOfDay":"evening","dayOfWeek":5,"clickCount_prev2":912,"totalSignificantAppLaunchCount_prev2":66,"phoneUsageTime_prev2":1479699,"unlockCount_prev2":26,"uniqueAppsLaunched_prev2":14},{"action":false,"timeAppLastUsed":"immediate","timeOfDay":"evening","dayOfWeek":5,"clickCount_prev2":912,"totalSignificantAppLaunchCount_prev2":66,"phoneUsageTime_prev2":1479699,"unlockCount_prev2":26,"uniqueAppsLaunched_prev2":14},{"action":false,"timeAppLastUsed":"immediate","timeOfDay":"evening","dayOfWeek":5,"clickCount_prev2":912,"totalSignificantAppLaunchCount_prev2":66,"phoneUsageTime_prev2":1479699,"unlockCount_prev2":26,"uniqueAppsLaunched_prev2":14},{"action":false,"timeAppLastUsed":"few mins","timeOfDay":"evening","dayOfWeek":5,"clickCount_prev2":912,"totalSignificantAppLaunchCount_prev2":66,"phoneUsageTime_prev2":1479699,"unlockCount_prev2":26,"uniqueAppsLaunched_prev2":14},{"action":false,"timeAppLastUsed":"within half hour","timeOfDay":"evening","dayOfWeek":5,"clickCount_prev2":912,"totalSignificantAppLaunchCount_prev2":66,"phoneUsageTime_prev2":1479699,"unlockCount_prev2":26,"uniqueAppsLaunched_prev2":14},{"action":false,"timeAppLastUsed":"few mins","timeOfDay":"evening","dayOfWeek":5,"clickCount_prev2":912,"totalSignificantAppLaunchCount_prev2":66,"phoneUsageTime_prev2":1479699,"unlockCount_prev2":26,"uniqueAppsLaunched_prev2":14},{"action":false,"timeAppLastUsed":"few mins","timeOfDay":"evening","dayOfWeek":5,"clickCount_prev2":912,"totalSignificantAppLaunchCount_prev2":66,"phoneUsageTime_prev2":1479699,"unlockCount_prev2":26,"uniqueAppsLaunched_prev2":14},{"action":false,"timeAppLastUsed":"few mins","timeOfDay":"evening","dayOfWeek":5,"clickCount_prev2":912,"totalSignificantAppLaunchCount_prev2":66,"phoneUsageTime_prev2":1479699,"unlockCount_prev2":26,"uniqueAppsLaunched_prev2":14},{"action":true,"timeAppLastUsed":"immediate","timeOfDay":"evening","dayOfWeek":5,"clickCount_prev2":912,"totalSignificantAppLaunchCount_prev2":66,"phoneUsageTime_prev2":1479699,"unlockCount_prev2":26,"uniqueAppsLaunched_prev2":14},{"action":false,"timeAppLastUsed":"immediate","timeOfDay":"evening","dayOfWeek":5,"clickCount_prev2":912,"totalSignificantAppLaunchCount_prev2":66,"phoneUsageTime_prev2":1479699,"unlockCount_prev2":26,"uniqueAppsLaunched_prev2":14},{"action":false,"timeAppLastUsed":"immediate","timeOfDay":"evening","dayOfWeek":5,"clickCount_prev2":912,"totalSignificantAppLaunchCount_prev2":66,"phoneUsageTime_prev2":1479699,"unlockCount_prev2":26,"uniqueAppsLaunched_prev2":14},{"action":true,"timeAppLastUsed":"within half hour","timeOfDay":"evening","dayOfWeek":5,"clickCount_prev2":912,"totalSignificantAppLaunchCount_prev2":66,"phoneUsageTime_prev2":1479699,"unlockCount_prev2":26,"uniqueAppsLaunched_prev2":14},{"action":true,"timeAppLastUsed":"immediate","timeOfDay":"evening","dayOfWeek":5,"clickCount_prev2":912,"totalSignificantAppLaunchCount_prev2":66,"phoneUsageTime_prev2":1479699,"unlockCount_prev2":26,"uniqueAppsLaunched_prev2":14},{"action":true,"timeAppLastUsed":"few mins","timeOfDay":"evening","dayOfWeek":5,"clickCount_prev2":781,"totalSignificantAppLaunchCount_prev2":31,"phoneUsageTime_prev2":1287438,"unlockCount_prev2":10,"uniqueAppsLaunched_prev2":11},{"action":true,"timeAppLastUsed":"immediate","timeOfDay":"night","dayOfWeek":5,"clickCount_prev2":781,"totalSignificantAppLaunchCount_prev2":31,"phoneUsageTime_prev2":1287438,"unlockCount_prev2":10,"uniqueAppsLaunched_prev2":11},{"action":false,"timeAppLastUsed":"immediate","timeOfDay":"night","dayOfWeek":5,"clickCount_prev2":781,"totalSignificantAppLaunchCount_prev2":31,"phoneUsageTime_prev2":1287438,"unlockCount_prev2":10,"uniqueAppsLaunched_prev2":11},{"action":true,"timeAppLastUsed":"few mins","timeOfDay":"night","dayOfWeek":5,"clickCount_prev2":781,"totalSignificantAppLaunchCount_prev2":31,"phoneUsageTime_prev2":1287438,"unlockCount_prev2":10,"uniqueAppsLaunched_prev2":11},{"action":false,"timeAppLastUsed":"within half hour","timeOfDay":"night","dayOfWeek":5,"clickCount_prev2":781,"totalSignificantAppLaunchCount_prev2":31,"phoneUsageTime_prev2":1287438,"unlockCount_prev2":10,"uniqueAppsLaunched_prev2":11},{"action":false,"timeAppLastUsed":"within half hour","timeOfDay":"night","dayOfWeek":5,"clickCount_prev2":781,"totalSignificantAppLaunchCount_prev2":31,"phoneUsageTime_prev2":1287438,"unlockCount_prev2":10,"uniqueAppsLaunched_prev2":11},{"action":false,"timeAppLastUsed":"within few hours","timeOfDay":"early-morning","dayOfWeek":6,"clickCount_prev2":134,"totalSignificantAppLaunchCount_prev2":1,"phoneUsageTime_prev2":192074,"unlockCount_prev2":1,"uniqueAppsLaunched_prev2":1},{"action":true,"timeAppLastUsed":"immediate","timeOfDay":"morning","dayOfWeek":6,"clickCount_prev2":626,"totalSignificantAppLaunchCount_prev2":110,"phoneUsageTime_prev2":1393708,"unlockCount_prev2":3,"uniqueAppsLaunched_prev2":19},{"action":true,"timeAppLastUsed":"immediate","timeOfDay":"morning","dayOfWeek":6,"clickCount_prev2":641,"totalSignificantAppLaunchCount_prev2":41,"phoneUsageTime_prev2":1188259,"unlockCount_prev2":8,"uniqueAppsLaunched_prev2":17},{"action":true,"timeAppLastUsed":"immediate","timeOfDay":"afternoon","dayOfWeek":6,"clickCount_prev2":1243,"totalSignificantAppLaunchCount_prev2":117,"phoneUsageTime_prev2":1441493,"unlockCount_prev2":14,"uniqueAppsLaunched_prev2":18},{"action":true,"timeAppLastUsed":"immediate","timeOfDay":"afternoon","dayOfWeek":6,"clickCount_prev2":1243,"totalSignificantAppLaunchCount_prev2":117,"phoneUsageTime_prev2":1441493,"unlockCount_prev2":14,"uniqueAppsLaunched_prev2":18},{"action":true,"timeAppLastUsed":"immediate","timeOfDay":"afternoon","dayOfWeek":6,"clickCount_prev2":329,"totalSignificantAppLaunchCount_prev2":63,"phoneUsageTime_prev2":565534,"unlockCount_prev2":10,"uniqueAppsLaunched_prev2":20},{"action":true,"timeAppLastUsed":"immediate","timeOfDay":"afternoon","dayOfWeek":6,"clickCount_prev2":329,"totalSignificantAppLaunchCount_prev2":63,"phoneUsageTime_prev2":565534,"unlockCount_prev2":10,"uniqueAppsLaunched_prev2":20},{"action":true,"timeAppLastUsed":"within 24 hours","timeOfDay":"afternoon","dayOfWeek":6,"clickCount_prev2":213,"totalSignificantAppLaunchCount_prev2":51,"phoneUsageTime_prev2":407282,"unlockCount_prev2":9,"uniqueAppsLaunched_prev2":14},{"action":true,"timeAppLastUsed":"immediate","timeOfDay":"evening","dayOfWeek":6,"clickCount_prev2":136,"totalSignificantAppLaunchCount_prev2":44,"phoneUsageTime_prev2":266789,"unlockCount_prev2":13,"uniqueAppsLaunched_prev2":9},{"action":true,"timeAppLastUsed":"immediate","timeOfDay":"night","dayOfWeek":6,"clickCount_prev2":649,"totalSignificantAppLaunchCount_prev2":37,"phoneUsageTime_prev2":710669,"unlockCount_prev2":6,"uniqueAppsLaunched_prev2":8},{"action":true,"timeAppLastUsed":"few mins","timeOfDay":"night","dayOfWeek":6,"clickCount_prev2":649,"totalSignificantAppLaunchCount_prev2":37,"phoneUsageTime_prev2":710669,"unlockCount_prev2":6,"uniqueAppsLaunched_prev2":8},{"action":true,"timeAppLastUsed":"immediate","timeOfDay":"night","dayOfWeek":6,"clickCount_prev2":649,"totalSignificantAppLaunchCount_prev2":37,"phoneUsageTime_prev2":710669,"unlockCount_prev2":6,"uniqueAppsLaunched_prev2":8},{"action":false,"timeAppLastUsed":"within 24 hours","timeOfDay":"afternoon","dayOfWeek":2,"clickCount_prev2":188,"totalSignificantAppLaunchCount_prev2":43,"phoneUsageTime_prev2":281680,"unlockCount_prev2":16,"uniqueAppsLaunched_prev2":13},{"action":false,"timeAppLastUsed":"immediate","timeOfDay":"afternoon","dayOfWeek":2,"clickCount_prev2":400,"totalSignificantAppLaunchCount_prev2":45,"phoneUsageTime_prev2":738715,"unlockCount_prev2":24,"uniqueAppsLaunched_prev2":11},{"action":false,"timeAppLastUsed":"immediate","timeOfDay":"afternoon","dayOfWeek":2,"clickCount_prev2":400,"totalSignificantAppLaunchCount_prev2":45,"phoneUsageTime_prev2":738715,"unlockCount_prev2":24,"uniqueAppsLaunched_prev2":11},{"action":false,"timeAppLastUsed":"immediate","timeOfDay":"afternoon","dayOfWeek":2,"clickCount_prev2":400,"totalSignificantAppLaunchCount_prev2":45,"phoneUsageTime_prev2":738715,"unlockCount_prev2":24,"uniqueAppsLaunched_prev2":11},{"action":false,"timeAppLastUsed":"immediate","timeOfDay":"afternoon","dayOfWeek":2,"clickCount_prev2":400,"totalSignificantAppLaunchCount_prev2":45,"phoneUsageTime_prev2":738715,"unlockCount_prev2":24,"uniqueAppsLaunched_prev2":11},{"action":false,"timeAppLastUsed":"immediate","timeOfDay":"afternoon","dayOfWeek":2,"clickCount_prev2":400,"totalSignificantAppLaunchCount_prev2":45,"phoneUsageTime_prev2":738715,"unlockCount_prev2":24,"uniqueAppsLaunched_prev2":11},{"action":false,"timeAppLastUsed":"immediate","timeOfDay":"afternoon","dayOfWeek":2,"clickCount_prev2":400,"totalSignificantAppLaunchCount_prev2":45,"phoneUsageTime_prev2":738715,"unlockCount_prev2":24,"uniqueAppsLaunched_prev2":11},{"action":false,"timeAppLastUsed":"immediate","timeOfDay":"afternoon","dayOfWeek":2,"clickCount_prev2":400,"totalSignificantAppLaunchCount_prev2":45,"phoneUsageTime_prev2":738715,"unlockCount_prev2":24,"uniqueAppsLaunched_prev2":11},{"action":false,"timeAppLastUsed":"immediate","timeOfDay":"afternoon","dayOfWeek":2,"clickCount_prev2":400,"totalSignificantAppLaunchCount_prev2":45,"phoneUsageTime_prev2":738715,"unlockCount_prev2":24,"uniqueAppsLaunched_prev2":11},{"action":false,"timeAppLastUsed":"immediate","timeOfDay":"afternoon","dayOfWeek":2,"clickCount_prev2":400,"totalSignificantAppLaunchCount_prev2":45,"phoneUsageTime_prev2":738715,"unlockCount_prev2":24,"uniqueAppsLaunched_prev2":11},{"action":false,"timeAppLastUsed":"immediate","timeOfDay":"afternoon","dayOfWeek":2,"clickCount_prev2":400,"totalSignificantAppLaunchCount_prev2":45,"phoneUsageTime_prev2":738715,"unlockCount_prev2":24,"uniqueAppsLaunched_prev2":11},{"action":true,"timeAppLastUsed":"immediate","timeOfDay":"afternoon","dayOfWeek":2,"clickCount_prev2":400,"totalSignificantAppLaunchCount_prev2":45,"phoneUsageTime_prev2":738715,"unlockCount_prev2":24,"uniqueAppsLaunched_prev2":11},{"action":true,"timeAppLastUsed":"within half hour","timeOfDay":"evening","dayOfWeek":2,"clickCount_prev2":1358,"totalSignificantAppLaunchCount_prev2":211,"phoneUsageTime_prev2":2730357,"unlockCount_prev2":11,"uniqueAppsLaunched_prev2":22},{"action":true,"timeAppLastUsed":"within half hour","timeOfDay":"evening","dayOfWeek":2,"clickCount_prev2":1358,"totalSignificantAppLaunchCount_prev2":211,"phoneUsageTime_prev2":2730357,"unlockCount_prev2":11,"uniqueAppsLaunched_prev2":22},{"action":true,"timeAppLastUsed":"immediate","timeOfDay":"evening","dayOfWeek":2,"clickCount_prev2":1338,"totalSignificantAppLaunchCount_prev2":174,"phoneUsageTime_prev2":2272126,"unlockCount_prev2":11,"uniqueAppsLaunched_prev2":22},{"action":true,"timeAppLastUsed":"immediate","timeOfDay":"evening","dayOfWeek":2,"clickCount_prev2":1338,"totalSignificantAppLaunchCount_prev2":174,"phoneUsageTime_prev2":2272126,"unlockCount_prev2":11,"uniqueAppsLaunched_prev2":22},{"action":false,"timeAppLastUsed":"within last week","timeOfDay":"morning","dayOfWeek":3,"clickCount_prev2":153,"totalSignificantAppLaunchCount_prev2":45,"phoneUsageTime_prev2":431805,"unlockCount_prev2":15,"uniqueAppsLaunched_prev2":13},{"action":true,"timeAppLastUsed":"within last week","timeOfDay":"morning","dayOfWeek":3,"clickCount_prev2":153,"totalSignificantAppLaunchCount_prev2":45,"phoneUsageTime_prev2":431805,"unlockCount_prev2":15,"uniqueAppsLaunched_prev2":13},{"action":false,"timeAppLastUsed":"immediate","timeOfDay":"morning","dayOfWeek":3,"clickCount_prev2":217,"totalSignificantAppLaunchCount_prev2":57,"phoneUsageTime_prev2":470178,"unlockCount_prev2":17,"uniqueAppsLaunched_prev2":15},{"action":true,"timeAppLastUsed":"within hour","timeOfDay":"morning","dayOfWeek":3,"clickCount_prev2":217,"totalSignificantAppLaunchCount_prev2":57,"phoneUsageTime_prev2":470178,"unlockCount_prev2":17,"uniqueAppsLaunched_prev2":15},{"action":true,"timeAppLastUsed":"immediate","timeOfDay":"morning","dayOfWeek":3,"clickCount_prev2":217,"totalSignificantAppLaunchCount_prev2":57,"phoneUsageTime_prev2":470178,"unlockCount_prev2":17,"uniqueAppsLaunched_prev2":15},{"action":true,"timeAppLastUsed":"within hour","timeOfDay":"morning","dayOfWeek":3,"clickCount_prev2":284,"totalSignificantAppLaunchCount_prev2":59,"phoneUsageTime_prev2":537725,"unlockCount_prev2":22,"uniqueAppsLaunched_prev2":21},{"action":true,"timeAppLastUsed":"within hour","timeOfDay":"morning","dayOfWeek":3,"clickCount_prev2":180,"totalSignificantAppLaunchCount_prev2":31,"phoneUsageTime_prev2":328584,"unlockCount_prev2":14,"uniqueAppsLaunched_prev2":14},{"action":true,"timeAppLastUsed":"within 24 hours","timeOfDay":"morning","dayOfWeek":3,"clickCount_prev2":113,"totalSignificantAppLaunchCount_prev2":15,"phoneUsageTime_prev2":169526,"unlockCount_prev2":8,"uniqueAppsLaunched_prev2":8},{"action":false,"timeAppLastUsed":"immediate","timeOfDay":"afternoon","dayOfWeek":3,"clickCount_prev2":99,"totalSignificantAppLaunchCount_prev2":28,"phoneUsageTime_prev2":186084,"unlockCount_prev2":12,"uniqueAppsLaunched_prev2":6},{"action":false,"timeAppLastUsed":"immediate","timeOfDay":"afternoon","dayOfWeek":3,"clickCount_prev2":99,"totalSignificantAppLaunchCount_prev2":28,"phoneUsageTime_prev2":186084,"unlockCount_prev2":12,"uniqueAppsLaunched_prev2":6},{"action":false,"timeAppLastUsed":"immediate","timeOfDay":"afternoon","dayOfWeek":3,"clickCount_prev2":99,"totalSignificantAppLaunchCount_prev2":28,"phoneUsageTime_prev2":186084,"unlockCount_prev2":12,"uniqueAppsLaunched_prev2":6},{"action":true,"timeAppLastUsed":"immediate","timeOfDay":"afternoon","dayOfWeek":3,"clickCount_prev2":416,"totalSignificantAppLaunchCount_prev2":87,"phoneUsageTime_prev2":720772,"unlockCount_prev2":16,"uniqueAppsLaunched_prev2":17},{"action":false,"timeAppLastUsed":"immediate","timeOfDay":"afternoon","dayOfWeek":3,"clickCount_prev2":452,"totalSignificantAppLaunchCount_prev2":58,"phoneUsageTime_prev2":687881,"unlockCount_prev2":18,"uniqueAppsLaunched_prev2":14},{"action":false,"timeAppLastUsed":"immediate","timeOfDay":"afternoon","dayOfWeek":3,"clickCount_prev2":452,"totalSignificantAppLaunchCount_prev2":58,"phoneUsageTime_prev2":687881,"unlockCount_prev2":18,"uniqueAppsLaunched_prev2":14},{"action":true,"timeAppLastUsed":"immediate","timeOfDay":"afternoon","dayOfWeek":3,"clickCount_prev2":485,"totalSignificantAppLaunchCount_prev2":44,"phoneUsageTime_prev2":597975,"unlockCount_prev2":13,"uniqueAppsLaunched_prev2":13},{"action":false,"timeAppLastUsed":"immediate","timeOfDay":"afternoon","dayOfWeek":3,"clickCount_prev2":485,"totalSignificantAppLaunchCount_prev2":44,"phoneUsageTime_prev2":597975,"unlockCount_prev2":13,"uniqueAppsLaunched_prev2":13},{"action":false,"timeAppLastUsed":"immediate","timeOfDay":"afternoon","dayOfWeek":3,"clickCount_prev2":485,"totalSignificantAppLaunchCount_prev2":44,"phoneUsageTime_prev2":597975,"unlockCount_prev2":13,"uniqueAppsLaunched_prev2":13},{"action":false,"timeAppLastUsed":"immediate","timeOfDay":"afternoon","dayOfWeek":3,"clickCount_prev2":485,"totalSignificantAppLaunchCount_prev2":44,"phoneUsageTime_prev2":597975,"unlockCount_prev2":13,"uniqueAppsLaunched_prev2":13},{"action":true,"timeAppLastUsed":"immediate","timeOfDay":"evening","dayOfWeek":3,"clickCount_prev2":904,"totalSignificantAppLaunchCount_prev2":78,"phoneUsageTime_prev2":937963,"unlockCount_prev2":22,"uniqueAppsLaunched_prev2":14},{"action":true,"timeAppLastUsed":"immediate","timeOfDay":"evening","dayOfWeek":3,"clickCount_prev2":298,"totalSignificantAppLaunchCount_prev2":35,"phoneUsageTime_prev2":496102,"unlockCount_prev2":9,"uniqueAppsLaunched_prev2":8},{"action":false,"timeAppLastUsed":"immediate","timeOfDay":"night","dayOfWeek":3,"clickCount_prev2":21,"totalSignificantAppLaunchCount_prev2":12,"phoneUsageTime_prev2":35121,"unlockCount_prev2":2,"uniqueAppsLaunched_prev2":9},{"action":false,"timeAppLastUsed":"immediate","timeOfDay":"morning","dayOfWeek":4,"clickCount_prev2":229,"totalSignificantAppLaunchCount_prev2":31,"phoneUsageTime_prev2":781225,"unlockCount_prev2":14,"uniqueAppsLaunched_prev2":14},{"action":true,"timeAppLastUsed":"immediate","timeOfDay":"morning","dayOfWeek":4,"clickCount_prev2":104,"totalSignificantAppLaunchCount_prev2":28,"phoneUsageTime_prev2":239708,"unlockCount_prev2":11,"uniqueAppsLaunched_prev2":13},{"action":true,"timeAppLastUsed":"immediate","timeOfDay":"morning","dayOfWeek":4,"clickCount_prev2":34,"totalSignificantAppLaunchCount_prev2":21,"phoneUsageTime_prev2":43027,"unlockCount_prev2":11,"uniqueAppsLaunched_prev2":9},{"action":true,"timeAppLastUsed":"within half hour","timeOfDay":"afternoon","dayOfWeek":4,"clickCount_prev2":587,"totalSignificantAppLaunchCount_prev2":75,"phoneUsageTime_prev2":851789,"unlockCount_prev2":13,"uniqueAppsLaunched_prev2":17},{"action":false,"timeAppLastUsed":"immediate","timeOfDay":"afternoon","dayOfWeek":4,"clickCount_prev2":691,"totalSignificantAppLaunchCount_prev2":138,"phoneUsageTime_prev2":928618,"unlockCount_prev2":29,"uniqueAppsLaunched_prev2":15},{"action":true,"timeAppLastUsed":"immediate","timeOfDay":"afternoon","dayOfWeek":4,"clickCount_prev2":691,"totalSignificantAppLaunchCount_prev2":138,"phoneUsageTime_prev2":928618,"unlockCount_prev2":29,"uniqueAppsLaunched_prev2":15},{"action":true,"timeAppLastUsed":"immediate","timeOfDay":"afternoon","dayOfWeek":4,"clickCount_prev2":691,"totalSignificantAppLaunchCount_prev2":138,"phoneUsageTime_prev2":928618,"unlockCount_prev2":29,"uniqueAppsLaunched_prev2":15},{"action":true,"timeAppLastUsed":"immediate","timeOfDay":"evening","dayOfWeek":4,"clickCount_prev2":397,"totalSignificantAppLaunchCount_prev2":81,"phoneUsageTime_prev2":489497,"unlockCount_prev2":21,"uniqueAppsLaunched_prev2":11},{"action":true,"timeAppLastUsed":"immediate","timeOfDay":"evening","dayOfWeek":4,"clickCount_prev2":397,"totalSignificantAppLaunchCount_prev2":81,"phoneUsageTime_prev2":489497,"unlockCount_prev2":21,"uniqueAppsLaunched_prev2":11},{"action":true,"timeAppLastUsed":"immediate","timeOfDay":"evening","dayOfWeek":4,"clickCount_prev2":397,"totalSignificantAppLaunchCount_prev2":81,"phoneUsageTime_prev2":489497,"unlockCount_prev2":21,"uniqueAppsLaunched_prev2":11},{"action":true,"timeAppLastUsed":"immediate","timeOfDay":"evening","dayOfWeek":4,"clickCount_prev2":397,"totalSignificantAppLaunchCount_prev2":81,"phoneUsageTime_prev2":489497,"unlockCount_prev2":21,"uniqueAppsLaunched_prev2":11},{"action":true,"timeAppLastUsed":"immediate","timeOfDay":"evening","dayOfWeek":4,"clickCount_prev2":397,"totalSignificantAppLaunchCount_prev2":81,"phoneUsageTime_prev2":489497,"unlockCount_prev2":21,"uniqueAppsLaunched_prev2":11},{"action":true,"timeAppLastUsed":"within half hour","timeOfDay":"evening","dayOfWeek":4,"clickCount_prev2":322,"totalSignificantAppLaunchCount_prev2":48,"phoneUsageTime_prev2":395431,"unlockCount_prev2":17,"uniqueAppsLaunched_prev2":14},{"action":true,"timeAppLastUsed":"immediate","timeOfDay":"evening","dayOfWeek":4,"clickCount_prev2":276,"totalSignificantAppLaunchCount_prev2":37,"phoneUsageTime_prev2":428779,"unlockCount_prev2":16,"uniqueAppsLaunched_prev2":15},{"action":false,"timeAppLastUsed":"immediate","timeOfDay":"night","dayOfWeek":4,"clickCount_prev2":133,"totalSignificantAppLaunchCount_prev2":31,"phoneUsageTime_prev2":169533,"unlockCount_prev2":14,"uniqueAppsLaunched_prev2":15},{"action":false,"timeAppLastUsed":"immediate","timeOfDay":"night","dayOfWeek":4,"clickCount_prev2":133,"totalSignificantAppLaunchCount_prev2":31,"phoneUsageTime_prev2":169533,"unlockCount_prev2":14,"uniqueAppsLaunched_prev2":15},{"action":true,"timeAppLastUsed":"within half hour","timeOfDay":"morning","dayOfWeek":5,"clickCount_prev2":826,"totalSignificantAppLaunchCount_prev2":119,"phoneUsageTime_prev2":1992526,"unlockCount_prev2":19,"uniqueAppsLaunched_prev2":25},{"action":true,"timeAppLastUsed":"within hour","timeOfDay":"afternoon","dayOfWeek":5,"clickCount_prev2":373,"totalSignificantAppLaunchCount_prev2":75,"phoneUsageTime_prev2":991635,"unlockCount_prev2":14,"uniqueAppsLaunched_prev2":17},{"action":true,"timeAppLastUsed":"within 24 hours","timeOfDay":"afternoon","dayOfWeek":5,"clickCount_prev2":390,"totalSignificantAppLaunchCount_prev2":47,"phoneUsageTime_prev2":650245,"unlockCount_prev2":12,"uniqueAppsLaunched_prev2":13},{"action":true,"timeAppLastUsed":"within 24 hours","timeOfDay":"afternoon","dayOfWeek":5,"clickCount_prev2":390,"totalSignificantAppLaunchCount_prev2":47,"phoneUsageTime_prev2":650245,"unlockCount_prev2":12,"uniqueAppsLaunched_prev2":13},{"action":true,"timeAppLastUsed":"within 24 hours","timeOfDay":"afternoon","dayOfWeek":5,"clickCount_prev2":44,"totalSignificantAppLaunchCount_prev2":16,"phoneUsageTime_prev2":55892,"unlockCount_prev2":7,"uniqueAppsLaunched_prev2":6},{"action":true,"timeAppLastUsed":"immediate","timeOfDay":"evening","dayOfWeek":5,"clickCount_prev2":230,"totalSignificantAppLaunchCount_prev2":31,"phoneUsageTime_prev2":472142,"unlockCount_prev2":18,"uniqueAppsLaunched_prev2":14},{"action":true,"timeAppLastUsed":"immediate","timeOfDay":"evening","dayOfWeek":5,"clickCount_prev2":230,"totalSignificantAppLaunchCount_prev2":31,"phoneUsageTime_prev2":472142,"unlockCount_prev2":18,"uniqueAppsLaunched_prev2":14},{"action":false,"timeAppLastUsed":"within few hours","timeOfDay":"evening","dayOfWeek":5,"clickCount_prev2":230,"totalSignificantAppLaunchCount_prev2":31,"phoneUsageTime_prev2":472142,"unlockCount_prev2":18,"uniqueAppsLaunched_prev2":14},{"action":true,"timeAppLastUsed":"immediate","timeOfDay":"morning","dayOfWeek":6,"clickCount_prev2":856,"totalSignificantAppLaunchCount_prev2":92,"phoneUsageTime_prev2":1826532,"unlockCount_prev2":14,"uniqueAppsLaunched_prev2":20},{"action":false,"timeAppLastUsed":"within half hour","timeOfDay":"morning","dayOfWeek":6,"clickCount_prev2":1108,"totalSignificantAppLaunchCount_prev2":79,"phoneUsageTime_prev2":2943460,"unlockCount_prev2":16,"uniqueAppsLaunched_prev2":21},{"action":false,"timeAppLastUsed":"immediate","timeOfDay":"morning","dayOfWeek":6,"clickCount_prev2":1264,"totalSignificantAppLaunchCount_prev2":82,"phoneUsageTime_prev2":3378574,"unlockCount_prev2":17,"uniqueAppsLaunched_prev2":25},{"action":true,"timeAppLastUsed":"immediate","timeOfDay":"night","dayOfWeek":6,"clickCount_prev2":71,"totalSignificantAppLaunchCount_prev2":5,"phoneUsageTime_prev2":162995,"unlockCount_prev2":1,"uniqueAppsLaunched_prev2":5},{"action":true,"timeAppLastUsed":"within last week","timeOfDay":"night","dayOfWeek":6,"clickCount_prev2":71,"totalSignificantAppLaunchCount_prev2":5,"phoneUsageTime_prev2":162995,"unlockCount_prev2":1,"uniqueAppsLaunched_prev2":5},{"action":false,"timeAppLastUsed":"immediate","timeOfDay":"morning","dayOfWeek":5,"clickCount_prev2":344,"totalSignificantAppLaunchCount_prev2":25,"phoneUsageTime_prev2":878860,"unlockCount_prev2":4,"uniqueAppsLaunched_prev2":14},{"action":true,"timeAppLastUsed":"immediate","timeOfDay":"morning","dayOfWeek":5,"clickCount_prev2":641,"totalSignificantAppLaunchCount_prev2":74,"phoneUsageTime_prev2":826317,"unlockCount_prev2":23,"uniqueAppsLaunched_prev2":15},{"action":true,"timeAppLastUsed":"immediate","timeOfDay":"morning","dayOfWeek":5,"clickCount_prev2":641,"totalSignificantAppLaunchCount_prev2":74,"phoneUsageTime_prev2":826317,"unlockCount_prev2":23,"uniqueAppsLaunched_prev2":15},{"action":true,"timeAppLastUsed":"immediate","timeOfDay":"morning","dayOfWeek":5,"clickCount_prev2":641,"totalSignificantAppLaunchCount_prev2":74,"phoneUsageTime_prev2":826317,"unlockCount_prev2":23,"uniqueAppsLaunched_prev2":15},{"action":true,"timeAppLastUsed":"immediate","timeOfDay":"morning","dayOfWeek":5,"clickCount_prev2":641,"totalSignificantAppLaunchCount_prev2":74,"phoneUsageTime_prev2":826317,"unlockCount_prev2":23,"uniqueAppsLaunched_prev2":15},{"action":true,"timeAppLastUsed":"immediate","timeOfDay":"morning","dayOfWeek":5,"clickCount_prev2":641,"totalSignificantAppLaunchCount_prev2":74,"phoneUsageTime_prev2":826317,"unlockCount_prev2":23,"uniqueAppsLaunched_prev2":15},{"action":true,"timeAppLastUsed":"immediate","timeOfDay":"morning","dayOfWeek":5,"clickCount_prev2":641,"totalSignificantAppLaunchCount_prev2":74,"phoneUsageTime_prev2":826317,"unlockCount_prev2":23,"uniqueAppsLaunched_prev2":15},{"action":false,"timeAppLastUsed":"immediate","timeOfDay":"morning","dayOfWeek":5,"clickCount_prev2":663,"totalSignificantAppLaunchCount_prev2":102,"phoneUsageTime_prev2":1034065,"unlockCount_prev2":26,"uniqueAppsLaunched_prev2":17},{"action":true,"timeAppLastUsed":"immediate","timeOfDay":"morning","dayOfWeek":5,"clickCount_prev2":1039,"totalSignificantAppLaunchCount_prev2":224,"phoneUsageTime_prev2":1998560,"unlockCount_prev2":22,"uniqueAppsLaunched_prev2":18},{"action":true,"timeAppLastUsed":"immediate","timeOfDay":"morning","dayOfWeek":5,"clickCount_prev2":1039,"totalSignificantAppLaunchCount_prev2":224,"phoneUsageTime_prev2":1998560,"unlockCount_prev2":22,"uniqueAppsLaunched_prev2":18},{"action":true,"timeAppLastUsed":"immediate","timeOfDay":"morning","dayOfWeek":5,"clickCount_prev2":1039,"totalSignificantAppLaunchCount_prev2":224,"phoneUsageTime_prev2":1998560,"unlockCount_prev2":22,"uniqueAppsLaunched_prev2":18},{"action":true,"timeAppLastUsed":"immediate","timeOfDay":"afternoon","dayOfWeek":5,"clickCount_prev2":1130,"totalSignificantAppLaunchCount_prev2":180,"phoneUsageTime_prev2":2488375,"unlockCount_prev2":11,"uniqueAppsLaunched_prev2":14},{"action":true,"timeAppLastUsed":"immediate","timeOfDay":"afternoon","dayOfWeek":5,"clickCount_prev2":1020,"totalSignificantAppLaunchCount_prev2":69,"phoneUsageTime_prev2":2327553,"unlockCount_prev2":10,"uniqueAppsLaunched_prev2":12},{"action":true,"timeAppLastUsed":"few mins","timeOfDay":"afternoon","dayOfWeek":5,"clickCount_prev2":562,"totalSignificantAppLaunchCount_prev2":57,"phoneUsageTime_prev2":1398824,"unlockCount_prev2":10,"uniqueAppsLaunched_prev2":12},{"action":true,"timeAppLastUsed":"within 24 hours","timeOfDay":"morning","dayOfWeek":6,"clickCount_prev2":626,"totalSignificantAppLaunchCount_prev2":41,"phoneUsageTime_prev2":1755355,"unlockCount_prev2":5,"uniqueAppsLaunched_prev2":19},{"action":false,"timeAppLastUsed":"immediate","timeOfDay":"afternoon","dayOfWeek":6,"clickCount_prev2":457,"totalSignificantAppLaunchCount_prev2":60,"phoneUsageTime_prev2":1213073,"unlockCount_prev2":7,"uniqueAppsLaunched_prev2":16},{"action":true,"timeAppLastUsed":"immediate","timeOfDay":"afternoon","dayOfWeek":6,"clickCount_prev2":457,"totalSignificantAppLaunchCount_prev2":60,"phoneUsageTime_prev2":1213073,"unlockCount_prev2":7,"uniqueAppsLaunched_prev2":16},{"action":true,"timeAppLastUsed":"immediate","timeOfDay":"afternoon","dayOfWeek":6,"clickCount_prev2":631,"totalSignificantAppLaunchCount_prev2":64,"phoneUsageTime_prev2":1365471,"unlockCount_prev2":5,"uniqueAppsLaunched_prev2":16},{"action":true,"timeAppLastUsed":"immediate","timeOfDay":"afternoon","dayOfWeek":6,"clickCount_prev2":631,"totalSignificantAppLaunchCount_prev2":64,"phoneUsageTime_prev2":1365471,"unlockCount_prev2":5,"uniqueAppsLaunched_prev2":16},{"action":true,"timeAppLastUsed":"immediate","timeOfDay":"evening","dayOfWeek":6,"clickCount_prev2":631,"totalSignificantAppLaunchCount_prev2":64,"phoneUsageTime_prev2":1365471,"unlockCount_prev2":5,"uniqueAppsLaunched_prev2":16},{"action":false,"timeAppLastUsed":"within few hours","timeOfDay":"morning","dayOfWeek":0,"clickCount_prev2":452,"totalSignificantAppLaunchCount_prev2":63,"phoneUsageTime_prev2":445719,"unlockCount_prev2":10,"uniqueAppsLaunched_prev2":7},{"action":false,"timeAppLastUsed":"within few hours","timeOfDay":"morning","dayOfWeek":0,"clickCount_prev2":452,"totalSignificantAppLaunchCount_prev2":63,"phoneUsageTime_prev2":445719,"unlockCount_prev2":10,"uniqueAppsLaunched_prev2":7},{"action":true,"timeAppLastUsed":"immediate","timeOfDay":"morning","dayOfWeek":0,"clickCount_prev2":452,"totalSignificantAppLaunchCount_prev2":63,"phoneUsageTime_prev2":445719,"unlockCount_prev2":10,"uniqueAppsLaunched_prev2":7},{"action":true,"timeAppLastUsed":"immediate","timeOfDay":"morning","dayOfWeek":0,"clickCount_prev2":452,"totalSignificantAppLaunchCount_prev2":63,"phoneUsageTime_prev2":445719,"unlockCount_prev2":10,"uniqueAppsLaunched_prev2":7},{"action":true,"timeAppLastUsed":"immediate","timeOfDay":"morning","dayOfWeek":0,"clickCount_prev2":1070,"totalSignificantAppLaunchCount_prev2":67,"phoneUsageTime_prev2":499159,"unlockCount_prev2":14,"uniqueAppsLaunched_prev2":13},{"action":true,"timeAppLastUsed":"immediate","timeOfDay":"morning","dayOfWeek":0,"clickCount_prev2":588,"totalSignificantAppLaunchCount_prev2":48,"phoneUsageTime_prev2":256291,"unlockCount_prev2":7,"uniqueAppsLaunched_prev2":7},{"action":false,"timeAppLastUsed":"within 24 hours","timeOfDay":"afternoon","dayOfWeek":0,"clickCount_prev2":588,"totalSignificantAppLaunchCount_prev2":48,"phoneUsageTime_prev2":256291,"unlockCount_prev2":7,"uniqueAppsLaunched_prev2":7},{"action":false,"timeAppLastUsed":"within 24 hours","timeOfDay":"afternoon","dayOfWeek":0,"clickCount_prev2":588,"totalSignificantAppLaunchCount_prev2":48,"phoneUsageTime_prev2":256291,"unlockCount_prev2":7,"uniqueAppsLaunched_prev2":7},{"action":true,"timeAppLastUsed":"immediate","timeOfDay":"afternoon","dayOfWeek":0,"clickCount_prev2":588,"totalSignificantAppLaunchCount_prev2":48,"phoneUsageTime_prev2":256291,"unlockCount_prev2":7,"uniqueAppsLaunched_prev2":7}]